{"cameraMode":{"drawMode":0,"name":"Shaded","section":"Shading Mode"},"sceneLighting":false,"audioPlay":false,"sceneViewState":{"m_AlwaysRefresh":false,"showFog":true,"showSkybox":false,"showFlares":true,"showImageEffects":true,"showParticleSystems":true,"showVisualEffectGraphs":true,"m_FxEnabled":true},"in2DMode":false,"pivot":{"x":-1.1920928955078126e-7,"y":0.0,"z":-0.016353368759155275},"rotation":{"x":-0.027949132025241853,"y":-0.06488292664289475,"z":0.0017157153924927116,"w":-0.9977388978004456},"size":2.3576724529266359,"orthographic":false}